{
  "location": {
    "id": 5426720
  },
  "plan": {
    "id": 5428455
  },
  "clinic_location_id": "",
  "plan_code": "",
  "owner_first_name": "Olivia",
  "owner_last_name": "Wright",
  "address": "100 Argonaut",
  "city": "Morino Valley",
  "state": "CA",
  "zip": "92551",
  "country": "US",
  "mobile": "1234567890",
  "phone": "0987654321",
  "email": "randomemail@random.com",
  "owner_id": "10001",
  "pet_id": "12341161",
  "pet_name": "Cece",
  "age": "1Y 2M",
  "gender": "",
  "card_name": "Visa",
  "payment_name": "Olivia Wright",
  "expiration_month": "1",
  "expiration_year": 2099,
  "account_number": 1234,
  "optional_plan_services": []
}