[
  {
    "id":1000012486,
    "plan":{
      "id":5428455,
      "shortDescription":"Puppy Wellness Plan"
    },
    "accountNbrForDisplay":"5354",
    "address1":"100 Argonaut",
    "address2":null,
    "ageGroupId":11,
    "bankAccountHolderType":"P",
    "bankAccountType":"C",
    "bankRoutingNbr":"122000496",
    "chargeCreditCheckFeeToConsumer":false,
    "chargePaymentFeeToConsumer":false,
    "checkNbr":null,
    "city":"Morino Valley",
    "contractDocCreated":null,
    "contractType":3,
    "country":"US",
    "createdByExternalUserCd":null,
    "creditCheckFeeAmt":10,
    "dateCreated":"2019-10-23T15:42:25Z",
    "downPaymentAmount":25,
    "email":"Olivia.Wright@ExtendCredit.com",
    "expirationMonth":null,
    "expirationYear":null,
    "externalClientCd":"1000",
    "externalLocationCd":null,
    "externalMemberCd":"1",
    "externalPaymentProfileId":"100846294",
    "externalPlanCd":null,
    "firstBillingDate":"2019-10-23T15:42:25Z",
    "firstName":"Olivia",
    "gatewayVaultId":null,
    "gender":null,
    "initialPaymentOption":2,
    "initiatedByProfessionalCd":null,
    "initiatedByProfessionalId":null,
    "institutionName":"UNION BANK",
    "lastName":"Wright",
    "lastUpdated":"2019-10-23T15:42:25Z",
    "location":{
      "id":5426720,
      "accountCd":"010265",
      "address1":"250 Commerce",
      "address2":"Suite 200 XXX",
      "city":"Irvine",
      "country":"USA",
      "externalLocationCd":"010265",
      "name":"SampleLocation",
      "postalCode":"92602",
      "resellerCustomerId":1995,
      "state":"CA"
    },
    "locationId":5426720,
    "memberAge":"1Y 2M",
    "memberName":"Cece",
    "middleInitial":null,
    "optionalPlanServices":[

    ],
    "payMethod":"ACH",
    "payOption":"ACH",
    "paymentAddress1":"100 Argonaut",
    "paymentAddress2":null,
    "paymentAmount":21.95,
    "paymentCity":"Morino Valley",
    "paymentCountry":"US",
    "paymentName":"Olivia Wright",
    "paymentPostalCode":"92551",
    "paymentServiceFeeAmt":3,
    "paymentState":"CA",
    "paymentTermCycle":"M",
    "paymentTermDuration":12,
    "paymentaddressSameAsAccount":true,
    "phone1":"9494814601",
    "phone1Type":"H",
    "phone2":"9494814602",
    "phone2Type":"W",
    "planAmount":263.4,
    "planId":5428455,
    "portalUsername":"test1234@test.com",
    "postalCode":"92551",
    "primaryCareProfessionalCd":null,
    "primaryCareProfessionalId":null,
    "salutation":"Mr.",
    "securityCode":null,
    "sendNotifications":true,
    "setupFeeAmt":10,
    "speciesId":1,
    "state":"CA",
    "status":"1",
    "totalCostAmount":288.4,
    "userId":5426455
  },
  {
    "id":1000012480,
    "plan":{
      "id":5428455,
      "shortDescription":"Puppy Wellness Plan"
    },
    "accountNbrForDisplay":"5354",
    "address1":"100 Argonaut",
    "address2":null,
    "ageGroupId":11,
    "bankAccountHolderType":"P",
    "bankAccountType":"C",
    "bankRoutingNbr":"122000496",
    "chargeCreditCheckFeeToConsumer":false,
    "chargePaymentFeeToConsumer":false,
    "checkNbr":null,
    "city":"Morino Valley",
    "contractDocCreated":null,
    "contractType":3,
    "country":"US",
    "createdByExternalUserCd":null,
    "creditCheckFeeAmt":10,
    "dateCreated":"2019-10-18T14:17:22Z",
    "downPaymentAmount":25,
    "email":"Olivia.Wright@ExtendCredit.com",
    "expirationMonth":null,
    "expirationYear":null,
    "externalClientCd":"1000",
    "externalLocationCd":null,
    "externalMemberCd":"1",
    "externalPaymentProfileId":"100842889",
    "externalPlanCd":null,
    "firstBillingDate":"2019-10-18T14:17:22Z",
    "firstName":"Olivia",
    "gatewayVaultId":null,
    "gender":null,
    "initialPaymentOption":2,
    "initiatedByProfessionalCd":null,
    "initiatedByProfessionalId":null,
    "institutionName":"UNION BANK",
    "lastName":"Wright",
    "lastUpdated":"2019-10-18T14:17:22Z",
    "location":{
      "id":5426720,
      "accountCd":"010265",
      "address1":"250 Commerce",
      "address2":"Suite 200 XXX",
      "city":"Irvine",
      "country":"USA",
      "externalLocationCd":"010265",
      "name":"SampleLocation",
      "postalCode":"92602",
      "resellerCustomerId":1995,
      "state":"CA"
    },
    "locationId":5426720,
    "memberAge":"1Y 2M",
    "memberName":"Cece",
    "middleInitial":null,
    "optionalPlanServices":[

    ],
    "payMethod":"ACH",
    "payOption":"ACH",
    "paymentAddress1":"100 Argonaut",
    "paymentAddress2":null,
    "paymentAmount":21.95,
    "paymentCity":"Morino Valley",
    "paymentCountry":"US",
    "paymentName":"Olivia Wright",
    "paymentPostalCode":"92551",
    "paymentServiceFeeAmt":3,
    "paymentState":"CA",
    "paymentTermCycle":"M",
    "paymentTermDuration":12,
    "paymentaddressSameAsAccount":true,
    "phone1":"9494814601",
    "phone1Type":"H",
    "phone2":"9494814602",
    "phone2Type":"W",
    "planAmount":263.4,
    "planId":5428455,
    "portalUsername":"test1234@test.com",
    "postalCode":"92551",
    "primaryCareProfessionalCd":null,
    "primaryCareProfessionalId":null,
    "salutation":"Mr.",
    "securityCode":null,
    "sendNotifications":true,
    "setupFeeAmt":10,
    "speciesId":1,
    "state":"CA",
    "status":"1",
    "totalCostAmount":288.4,
    "userId":5426455
  }
]